csdbe.py
csdbe-2.3.0.dist-info/WHEEL
csdbe-2.3.0.dist-info/METADATA
csdbe-2.3.0.dist-info/RECORD
