Metadata-Version: 2.1
Name: csdbe
Version: 2.3.0
Summary: This is a CSDBE(Coctail script discord bot editor) writen by Winter_coctail
License: Alpachi License 2.0
Author: Winter_coctail
Requires-Python: >=3.6,<4.0
Classifier: License :: Other/Proprietary License
Classifier: Programming Language :: Python :: 3
Classifier: Programming Language :: Python :: 3.6
Classifier: Programming Language :: Python :: 3.7
Classifier: Programming Language :: Python :: 3.8
Classifier: Programming Language :: Python :: 3.9
